asynctinydb/__init__.py
asynctinydb/database.py
asynctinydb/indices.py
asynctinydb/middlewares.py
asynctinydb/modifier.py
asynctinydb/mypy_plugin.py
asynctinydb/operations.py
asynctinydb/py.typed
asynctinydb/queries.py
asynctinydb/storages.py
asynctinydb/table.py
asynctinydb/transaction.py
asynctinydb/utils.py
asynctinydb/version.py
async_tinydb-1.7.3.dist-info/LICENSE
async_tinydb-1.7.3.dist-info/METADATA
async_tinydb-1.7.3.dist-info/WHEEL
async_tinydb-1.7.3.dist-info/RECORD
