Metadata-Version: 2.1
Name: async-tinydb
Version: 1.7.3
Summary: Yet Another Async TinyDB
Home-page: https://github.com/VermiIIi0n/async-tinydb
License: MIT
Keywords: database,nosql,async
Author: VermiIIi0n
Author-email: dungeon.behind0t@icloud.com
Requires-Python: >=3.10,<4.0
Classifier: Development Status :: 5 - Production/Stable
Classifier: Framework :: AsyncIO
Classifier: Framework :: Pytest
Classifier: Intended Audience :: Developers
Classifier: Intended Audience :: System Administrators
Classifier: License :: OSI Approved :: MIT License
Classifier: Operating System :: OS Independent
Classifier: Programming Language :: Python :: 3
Classifier: Programming Language :: Python :: 3.10
Classifier: Programming Language :: Python :: 3.11
Classifier: Programming Language :: Python :: 3.12
Classifier: Programming Language :: Python :: Implementation :: CPython
Classifier: Programming Language :: Python :: Implementation :: PyPy
Classifier: Topic :: Database
Classifier: Topic :: Database :: Database Engines/Servers
Classifier: Topic :: Utilities
Classifier: Typing :: Typed
Provides-Extra: all
Provides-Extra: compression
Provides-Extra: encryption
Requires-Dist: Brotli (>=1.0.9,<2.0.0) ; extra == "compression" or extra == "all"
Requires-Dist: blosc2 (>=0.4.1,<0.5.0) ; extra == "compression" or extra == "all"
Requires-Dist: cachetools (>=5.3.0,<6.0.0)
Requires-Dist: nest-asyncio (>=1.5.5,<2.0.0)
Requires-Dist: pycryptodome (>=3.15.0,<4.0.0) ; extra == "encryption" or extra == "all"
Requires-Dist: ujson (>5.4.0)
Requires-Dist: vermils (>=0.3.5,<0.4.0)
Project-URL: Issues, https://github.com/VermiIIi0n/async-tinydb/issues
